{
  "timestamp": "2026-05-06T20:12:12.863008",
  "opportunities": [
    {
      "chain": "ETHEREUM",
      "symbol": "ETH",
      "name": "Ether",
      "address": "0x0000000000000000000000000000000000000000",
      "price": 2409.2,
      "market_cap": 0.0,
      "liquidity": 588250.43,
      "volume_24h": 6799813.22,
      "price_change_24h": 1.15,
      "safety_score": 100,
      "total_score": 75.0,
      "url": "https://dexscreener.com/ethereum/0x00b9edc1583bf6ef09ff3a09f6c23ecb57fd7d0bb75625717ec81eed181e22d7"
    },
    {
      "chain": "ETHEREUM",
      "symbol": "ETH",
      "name": "Ether",
      "address": "0x0000000000000000000000000000000000000000",
      "price": 2409.59,
      "market_cap": 0.0,
      "liquidity": 1283669.7,
      "volume_24h": 5049270.28,
      "price_change_24h": 1.2,
      "safety_score": 100,
      "total_score": 75.0,
      "url": "https://dexscreener.com/ethereum/0x2287a9620adcbf6250dc71be9ee9b2d3a1ec85a464fc6f5c06669e8d07b61bba"
    },
    {
      "chain": "POLYGON",
      "symbol": "NWS",
      "name": "Nodewaves",
      "address": "0x13646e0E2d768D31B75d1A1e375e3E17F18567f2",
      "price": 3.573e-05,
      "market_cap": 278428.0,
      "liquidity": 19874.26,
      "volume_24h": 308924.7,
      "price_change_24h": -87.04,
      "safety_score": 100,
      "total_score": 75.0,
      "url": "https://dexscreener.com/polygon/0xb67d3eba00e7890fe1241bf4eec0ae08134ea715"
    },
    {
      "chain": "SOLANA",
      "symbol": "SOL",
      "name": "Sol The Trophy Tomato",
      "address": "jk1T35eWK41MBMM8AWoYVaNbjHEEQzMDetTsfnqpump",
      "price": 0.001591,
      "market_cap": 1305601.0,
      "liquidity": 198493.83,
      "volume_24h": 450000.29,
      "price_change_24h": 0.26,
      "safety_score": 100,
      "total_score": 70.0,
      "url": "https://dexscreener.com/solana/ccybxbmhr2o9vyz2wmjcrvi59wh42xkxf6qrzchbhpn5"
    },
    {
      "chain": "SOLANA",
      "symbol": "SOL",
      "name": "Solana",
      "address": "sosd5Q3DutGxMEaukBDmkPgsapMQz59jNjGWmhYcdTQ",
      "price": 143.2,
      "market_cap": 3293490.0,
      "liquidity": 2466971.96,
      "volume_24h": 210280.78,
      "price_change_24h": -0.23,
      "safety_score": 100,
      "total_score": 70.0,
      "url": "https://dexscreener.com/solana/3fkduervunskkygtyx1hkijmjvbiytdwybwxyw19n28t"
    },
    {
      "chain": "SOLANA",
      "symbol": "SOL",
      "name": "Solana",
      "address": "SooEj828BSjtgTecBRkqBJ4oquc713yyFZqbCawawoN",
      "price": 78.36,
      "market_cap": 9403845.0,
      "liquidity": 7050187.24,
      "volume_24h": 210279.96,
      "price_change_24h": -0.08,
      "safety_score": 100,
      "total_score": 70.0,
      "url": "https://dexscreener.com/solana/ghhuincofketz9rtgd1dghhoudajrw9ddadmx13jdgey"
    },
    {
      "chain": "SOLANA",
      "symbol": "SOL",
      "name": "Solana",
      "address": "sokhCSmzutMPPuNcxG1j6gYLowgiM8mswjJu8FBYm5r",
      "price": 92.43,
      "market_cap": 2310805.0,
      "liquidity": 901317.57,
      "volume_24h": 210279.09,
      "price_change_24h": -0.63,
      "safety_score": 100,
      "total_score": 70.0,
      "url": "https://dexscreener.com/solana/3ds5vzhbamv3fh5jsz221c7nbjlmaotwklclm5n7mtic"
    },
    {
      "chain": "ARBITRUM",
      "symbol": "ARB",
      "name": "Arbitrum",
      "address": "0x912CE59144191C1204E64559FE8253a0e49E6548",
      "price": 0.1252,
      "market_cap": 1252459800.0,
      "liquidity": 2115587.47,
      "volume_24h": 7120860.87,
      "price_change_24h": 4.91,
      "safety_score": 100,
      "total_score": 70.0,
      "url": "https://dexscreener.com/arbitrum/0xc6f780497a95e246eb9449f5e4770916dcd6396a"
    },
    {
      "chain": "OPTIMISM",
      "symbol": "OP",
      "name": "Optimism",
      "address": "0x4200000000000000000000000000000000000042",
      "price": 0.1364,
      "market_cap": 586019306.0,
      "liquidity": 572375.49,
      "volume_24h": 1571862.26,
      "price_change_24h": 4.91,
      "safety_score": 100,
      "total_score": 70.0,
      "url": "https://dexscreener.com/optimism/0x4dc22588ade05c40338a9d95a6da9dcee68bcd60"
    },
    {
      "chain": "SOLANA",
      "symbol": "SOL",
      "name": "Solana",
      "address": "BCWd9Gw3dGzjLiTqX3xnSFNJG8Jywrc7wUDtXW3E9F5n",
      "price": 84.29,
      "market_cap": 177029368.0,
      "liquidity": 176847281.6,
      "volume_24h": 202408.36,
      "price_change_24h": 0.0,
      "safety_score": 100,
      "total_score": 65.0,
      "url": "https://dexscreener.com/solana/5rceqe9vj7hxafgipzpgyz3wdnxcmlglz4midgjd8cfg"
    },
    {
      "chain": "ARBITRUM",
      "symbol": "ARB",
      "name": "Arbitrum",
      "address": "0x912CE59144191C1204E64559FE8253a0e49E6548",
      "price": 0.1251,
      "market_cap": 1251584792.0,
      "liquidity": 4063169.57,
      "volume_24h": 395523.48,
      "price_change_24h": 4.36,
      "safety_score": 100,
      "total_score": 65.0,
      "url": "https://dexscreener.com/arbitrum/0x689c96ceab93f5e131631d225d75dea3fd37747e"
    },
    {
      "chain": "ARBITRUM",
      "symbol": "ARB",
      "name": "Arbitrum",
      "address": "0x912CE59144191C1204E64559FE8253a0e49E6548",
      "price": 0.1252,
      "market_cap": 1252213725.0,
      "liquidity": 326075.63,
      "volume_24h": 176987.0,
      "price_change_24h": 4.95,
      "safety_score": 100,
      "total_score": 65.0,
      "url": "https://dexscreener.com/arbitrum/0xcda53b1f66614552f834ceef361a8d12a0b8dad8"
    },
    {
      "chain": "POLYGON",
      "symbol": "T3",
      "name": "T3",
      "address": "0xF125D03aA14e6544A2fE147AA997C6722d27300E",
      "price": 0.374,
      "market_cap": 5368328.0,
      "liquidity": 898989.78,
      "volume_24h": 13498.79,
      "price_change_24h": -4.16,
      "safety_score": 100,
      "total_score": 65.0,
      "url": "https://dexscreener.com/polygon/0xa631d042814547cf15f6f60ae4f36591fefe70a8"
    },
    {
      "chain": "OPTIMISM",
      "symbol": "OP",
      "name": "Optimism",
      "address": "0x4200000000000000000000000000000000000042",
      "price": 0.1361,
      "market_cap": 584699233.0,
      "liquidity": 157709.22,
      "volume_24h": 165025.08,
      "price_change_24h": 4.61,
      "safety_score": 100,
      "total_score": 65.0,
      "url": "https://dexscreener.com/optimism/0xebd5311bea1948e1441333976eadcfe5fbda777c"
    },
    {
      "chain": "OPTIMISM",
      "symbol": "OP",
      "name": "Optimism",
      "address": "0x4200000000000000000000000000000000000042",
      "price": 0.136,
      "market_cap": 584524242.0,
      "liquidity": 202883.28,
      "volume_24h": 156456.11,
      "price_change_24h": 4.57,
      "safety_score": 100,
      "total_score": 65.0,
      "url": "https://dexscreener.com/optimism/0xb533c12fb4e7b53b5524eab9b47d93ff6c7a456f"
    },
    {
      "chain": "ARBITRUM",
      "symbol": "ARB",
      "name": "Arbitrum",
      "address": "0x912CE59144191C1204E64559FE8253a0e49E6548",
      "price": 0.1252,
      "market_cap": 1252391318.0,
      "liquidity": 92290.42,
      "volume_24h": 232630.79,
      "price_change_24h": 4.92,
      "safety_score": 100,
      "total_score": 60.0,
      "url": "https://dexscreener.com/arbitrum/0xe51635ae8136abac44906a8f230c2d235e9c195f"
    },
    {
      "chain": "ARBITRUM",
      "symbol": "ARB",
      "name": "Arbitrum",
      "address": "0x912CE59144191C1204E64559FE8253a0e49E6548",
      "price": 0.125,
      "market_cap": 1250490578.0,
      "liquidity": 675282.78,
      "volume_24h": 42060.49,
      "price_change_24h": 4.77,
      "safety_score": 100,
      "total_score": 60.0,
      "url": "https://dexscreener.com/arbitrum/0xaebdca1bc8d89177ebe2308d62af5e74885dccc3"
    },
    {
      "chain": "OPTIMISM",
      "symbol": "OP",
      "name": "Optimism",
      "address": "0x4200000000000000000000000000000000000042",
      "price": 0.1364,
      "market_cap": 586166759.0,
      "liquidity": 275252.95,
      "volume_24h": 60113.65,
      "price_change_24h": 4.8,
      "safety_score": 100,
      "total_score": 60.0,
      "url": "https://dexscreener.com/optimism/0x68f5c0a2de713a54991e01858fd27a3832401849"
    },
    {
      "chain": "BSC",
      "symbol": "BSC",
      "name": "Binance Super Cycle",
      "address": "0x6331BF8D601f0D7F0d2101772af5137c418c4444",
      "price": 0.0002332,
      "market_cap": 233278.0,
      "liquidity": 85225.78,
      "volume_24h": 18844.04,
      "price_change_24h": 4.11,
      "safety_score": 80,
      "total_score": 57.0,
      "url": "https://dexscreener.com/bsc/0xff0a8df8c4a0332e28a4c94ebb3f633944b08a94"
    },
    {
      "chain": "POLYGON",
      "symbol": "APEPE",
      "name": "Ape and Pepe",
      "address": "0xA3f751662e282E83EC3cBc387d225Ca56dD63D3A",
      "price": 1.323e-06,
      "market_cap": 278011253.0,
      "liquidity": 21796.62,
      "volume_24h": 28005.75,
      "price_change_24h": -1.5,
      "safety_score": 100,
      "total_score": 55.0,
      "url": "https://dexscreener.com/polygon/0x00a59c2d0f0f4837028d47a391decbffc1e10608"
    },
    {
      "chain": "OPTIMISM",
      "symbol": "OP",
      "name": "Optimism",
      "address": "0x4200000000000000000000000000000000000042",
      "price": 0.1363,
      "market_cap": 585424181.0,
      "liquidity": 33074.46,
      "volume_24h": 37287.49,
      "price_change_24h": 4.78,
      "safety_score": 100,
      "total_score": 55.0,
      "url": "https://dexscreener.com/optimism/0xfc1f3296458f9b2a27a0b91dd7681c4020e09d05"
    }
  ],
  "errors": []
}